AUTHORS.md
CHANGELOG.md
LICENSE
MANIFEST.in
README.md
pyproject.toml
setup.cfg
setup.py
c-src/CMakeLists.txt
c-src/include/stoken_bfasst.h
c-src/src/stoken_bfasst.c
doc/Makefile
doc/conf.py
doc/index.rst
doc/make.bat
src/stoken_bfasst/__init__.py
src/stoken_bfasst/py.typed
src/stoken_bfasst.egg-info/PKG-INFO
src/stoken_bfasst.egg-info/SOURCES.txt
src/stoken_bfasst.egg-info/dependency_links.txt
src/stoken_bfasst.egg-info/top_level.txt
src/stoken_bfasst_core/__init__.py
src/stoken_bfasst_core/ctypes.py
src/stoken_bfasst_core/library_loader.py
src/stoken_bfasst_core/py.typed
src/stoken_bfasst_core/securid.py
tests/__init__.py
tests/conftest.py
tests/test_search.py
tests/test_securid.py