Metadata-Version: 2.1
Name: stoken-bfasst
Version: 1.1.0
Summary: Recover your RSA SecurID key from your memory dumps!
Author-email: Eduard Christian Dumitrescu <eduard.c.dumitrescu@gmail.com>
Maintainer-email: Eduard Christian Dumitrescu <eduard.c.dumitrescu@gmail.com>
License: Apache License (2.0)
Project-URL: Homepage, https://github.com/e-c-d/stoken_bfasst
Classifier: Programming Language :: Python :: 3
License-File: LICENSE
License-File: AUTHORS.md
